extras/__init__.py
extras/additionalMath.py
myMathModuletst-1.1.dist-info/METADATA
myMathModuletst-1.1.dist-info/WHEEL
myMathModuletst-1.1.dist-info/top_level.txt
myMathModuletst-1.1.dist-info/RECORD
