Metadata-Version: 2.1
Name: myMathModuletst
Version: 1.1
Summary: My first attempt to create a python package
Home-page: UNKNOWN
Author: Swaminathan S
Author-email: youremail@email.com
License: UNKNOWN
Keywords: python,first package
Platform: UNKNOWN
Classifier: Development Status :: 3 - Alpha
Classifier: Intended Audience :: Education
Classifier: Programming Language :: Python :: 2
Classifier: Programming Language :: Python :: 3
Classifier: Operating System :: MacOS :: MacOS X
Classifier: Operating System :: Microsoft :: Windows
